{
  "call": {
    "called_at": 1777796444,
    "classification": "DEVELOPING",
    "closed_at": null,
    "confidence": 61,
    "current_liquidity_usd": 17698.16,
    "current_mcap_usd": 52573.0,
    "current_price_usd": 0.00005257,
    "entry_liquidity_usd": 18700.66,
    "entry_mcap_usd": 58834.0,
    "entry_pair_dex": "pumpswap",
    "entry_price_usd": 0.00005883,
    "entry_top_holder_pct": 16.983641581928037,
    "exit_note": null,
    "exit_price_usd": null,
    "expires_at": 1777801844,
    "id": 148,
    "mint": "4mxWL7MkSQPLXV7DAmvXBS7HLUbB4WXZdmxibStfpump",
    "note": "I’m in Mike here: 58.8k cap, 130/min, 1.18 buys, no bundle/sniper noise. · horizon=MOONSHOT",
    "outcome_type": "active",
    "pct_from_call": -10.640829508754035,
    "peak_at": 1777796444,
    "peak_pct": -6.901240863505009,
    "source": "notifier",
    "status": "active",
    "symbol": "Mike",
    "thesis_url": null,
    "trough_at": 1777796500,
    "trough_pct": -10.419853816080227
  },
  "captured_at": 1777796607,
  "last_snapshot_ts": 1777796590,
  "snapshots": [
    {
      "bundle_pct": 0.0,
      "buys_h1": 317,
      "classification": "DEVELOPING",
      "confidence": 61,
      "distribution": 53,
      "forensics_computed_at": 1777796141,
      "holder_count": 256,
      "insider_pct": 0.0,
      "liquidity_usd": 18038.53,
      "mcap_usd": 54774.0,
      "momentum": 69,
      "pair_dex": "pumpswap",
      "price_change_h1": 58.73,
      "price_usd": 0.00005477,
      "sells_h1": 268,
      "smart_money_count": 0,
      "sniper_pct": 57.63848114291199,
      "spring": 61,
      "timestamp": 1777796444,
      "token_address": "4mxWL7MkSQPLXV7DAmvXBS7HLUbB4WXZdmxibStfpump",
      "top10_pct": 36.72112371985361,
      "top5_pct": 27.337556904479772,
      "top_holder_pct": 16.983641581928037,
      "tx_rate": 130.43478260869566,
      "velocity": 0.5,
      "volume_h1_usd": 25691.18
    },
    {
      "bundle_pct": 0.0,
      "buys_h1": 403,
      "classification": "STAIRCASE",
      "confidence": 72,
      "distribution": 54,
      "forensics_computed_at": 1777796141,
      "holder_count": 299,
      "insider_pct": 0.0,
      "liquidity_usd": 17704.79,
      "mcap_usd": 52708.0,
      "momentum": 73,
      "pair_dex": "pumpswap",
      "price_change_h1": 52.74,
      "price_usd": 0.0000527,
      "sells_h1": 339,
      "smart_money_count": 0,
      "sniper_pct": 57.63848114291199,
      "spring": 63,
      "timestamp": 1777796500,
      "token_address": "4mxWL7MkSQPLXV7DAmvXBS7HLUbB4WXZdmxibStfpump",
      "top10_pct": 37.209193175309984,
      "top5_pct": 27.152693858481083,
      "top_holder_pct": 16.733190477732286,
      "tx_rate": 90.9090909090909,
      "velocity": 1.0,
      "volume_h1_usd": 31727.05
    },
    {
      "bundle_pct": 0.0,
      "buys_h1": 403,
      "classification": "STAIRCASE",
      "confidence": 75,
      "distribution": 53,
      "forensics_computed_at": 1777796141,
      "holder_count": 299,
      "insider_pct": 0.0,
      "liquidity_usd": 17704.79,
      "mcap_usd": 52708.0,
      "momentum": 79,
      "pair_dex": "pumpswap",
      "price_change_h1": 52.74,
      "price_usd": 0.0000527,
      "sells_h1": 339,
      "smart_money_count": 0,
      "sniper_pct": 57.63848114291199,
      "spring": 66,
      "timestamp": 1777796522,
      "token_address": "4mxWL7MkSQPLXV7DAmvXBS7HLUbB4WXZdmxibStfpump",
      "top10_pct": 37.54968041884101,
      "top5_pct": 27.49318110201211,
      "top_holder_pct": 17.073677721263312,
      "tx_rate": 130.43478260869566,
      "velocity": 2.0,
      "volume_h1_usd": 31727.05
    },
    {
      "bundle_pct": 0.0,
      "buys_h1": 438,
      "classification": "DEVELOPING",
      "confidence": 61,
      "distribution": 53,
      "forensics_computed_at": 1777796141,
      "holder_count": 299,
      "insider_pct": 0.0,
      "liquidity_usd": 17814.79,
      "mcap_usd": 53324.0,
      "momentum": 69,
      "pair_dex": "pumpswap",
      "price_change_h1": 54.52,
      "price_usd": 0.00005332,
      "sells_h1": 369,
      "smart_money_count": 0,
      "sniper_pct": 57.63848114291199,
      "spring": 61,
      "timestamp": 1777796543,
      "token_address": "4mxWL7MkSQPLXV7DAmvXBS7HLUbB4WXZdmxibStfpump",
      "top10_pct": 36.819707103555714,
      "top5_pct": 27.436140288181875,
      "top_holder_pct": 17.08222496563014,
      "tx_rate": 115.38461538461539,
      "velocity": 0.5,
      "volume_h1_usd": 34470.43
    },
    {
      "bundle_pct": 0.0,
      "buys_h1": 438,
      "classification": "GRINDER",
      "confidence": 70,
      "distribution": 53,
      "forensics_computed_at": 1777796141,
      "holder_count": 321,
      "insider_pct": 0.0,
      "liquidity_usd": 17814.79,
      "mcap_usd": 53324.0,
      "momentum": 70,
      "pair_dex": "pumpswap",
      "price_change_h1": 54.52,
      "price_usd": 0.00005332,
      "sells_h1": 369,
      "smart_money_count": 0,
      "sniper_pct": 57.63848114291199,
      "spring": 61,
      "timestamp": 1777796567,
      "token_address": "4mxWL7MkSQPLXV7DAmvXBS7HLUbB4WXZdmxibStfpump",
      "top10_pct": 36.190161001471466,
      "top5_pct": 26.80659418609762,
      "top_holder_pct": 16.452678863545884,
      "tx_rate": 200.0,
      "velocity": 3.0,
      "volume_h1_usd": 34470.43
    },
    {
      "bundle_pct": 0.0,
      "buys_h1": 491,
      "classification": "DEVELOPING",
      "confidence": 60,
      "distribution": 54,
      "forensics_computed_at": 1777796141,
      "holder_count": 321,
      "insider_pct": 0.0,
      "liquidity_usd": 17698.16,
      "mcap_usd": 52573.0,
      "momentum": 65,
      "pair_dex": "pumpswap",
      "price_change_h1": 52.35,
      "price_usd": 0.00005257,
      "sells_h1": 385,
      "smart_money_count": 0,
      "sniper_pct": 57.63848114291199,
      "spring": 59,
      "timestamp": 1777796590,
      "token_address": "4mxWL7MkSQPLXV7DAmvXBS7HLUbB4WXZdmxibStfpump",
      "top10_pct": 36.58064727737461,
      "top5_pct": 27.197080462000763,
      "top_holder_pct": 16.843165139449027,
      "tx_rate": 88.23529411764707,
      "velocity": 1.3333333333333335,
      "volume_h1_usd": 39153.39
    }
  ]
}