{
  "call": {
    "called_at": 1777339105,
    "classification": "CURVE",
    "closed_at": null,
    "confidence": 58,
    "current_liquidity_usd": 0.0,
    "current_mcap_usd": 4010.2,
    "current_price_usd": 4.01e-6,
    "entry_liquidity_usd": 7711.64625595,
    "entry_mcap_usd": 40312.608766489546,
    "entry_pair_dex": "curve",
    "entry_price_usd": 0.00004031260876648954,
    "entry_top_holder_pct": 0.0,
    "exit_note": null,
    "exit_price_usd": null,
    "expires_at": 1777360705,
    "id": 34,
    "mint": "FNi1q77BXgDJf6HTMBWTpTFRJu2oaCPzah9zQjZvpump",
    "note": "horizon=SHORT source=curve fill=10.7% velocity=1.94sol/min alpha=59",
    "outcome_type": "active",
    "pct_from_call": -90.05274001683222,
    "peak_at": null,
    "peak_pct": null,
    "source": "curve",
    "status": "active",
    "symbol": "",
    "thesis_url": null,
    "trough_at": null,
    "trough_pct": null
  },
  "captured_at": 1777341893,
  "last_snapshot_ts": 0,
  "snapshots": []
}