{
  "active": [
    {
      "id": 26,
      "mint": "F4LYw83S51J4Dz9uZzeeGD1BbfYHJnEhF44dqyXepump",
      "symbol": "BLIMP",
      "classification": "STAIRCASE",
      "confidence": 77,
      "called_at": 1777187712,
      "expires_at": 1778397312,
      "note": "",
      "source": "notifier",
      "status": "active",
      "outcome_type": "active",
      "closed_at": null,
      "exit_price_usd": null,
      "exit_note": null,
      "entry_mcap_usd": 81662.0,
      "entry_price_usd": 0.00008166,
      "entry_liquidity_usd": 22402.04,
      "entry_top_holder_pct": 13.424463347019236,
      "entry_pair_dex": "pumpswap",
      "current_mcap_usd": 121346.0,
      "current_price_usd": 0.0001213,
      "current_liquidity_usd": 27998.51,
      "pct_from_call": 48.542738182708774
    },
    {
      "id": 25,
      "mint": "HmBdm8vbisABUjkxms6ZUnoaXbfwFM6ymxShWfAENaoi",
      "symbol": "EITHER",
      "classification": "STAIRCASE",
      "confidence": 75,
      "called_at": 1777187607,
      "expires_at": 1778397207,
      "note": "",
      "source": "notifier",
      "status": "active",
      "outcome_type": "active",
      "closed_at": null,
      "exit_price_usd": null,
      "exit_note": null,
      "entry_mcap_usd": 12700612.0,
      "entry_price_usd": 0.127,
      "entry_liquidity_usd": 304069.05,
      "entry_top_holder_pct": 5.000003334043528,
      "entry_pair_dex": "meteora",
      "current_mcap_usd": 13546663.0,
      "current_price_usd": 0.1354,
      "current_liquidity_usd": 314160.63,
      "pct_from_call": 6.614173228346454
    },
    {
      "id": 24,
      "mint": "FqSxniFXc3AeRAkcs3vvZ62xfKJNcgswDtNnKC3Vpump",
      "symbol": "Archangel",
      "classification": "STAIRCASE",
      "confidence": 77,
      "called_at": 1777187589,
      "expires_at": 1778397189,
      "note": "",
      "source": "notifier",
      "status": "active",
      "outcome_type": "active",
      "closed_at": null,
      "exit_price_usd": null,
      "exit_note": null,
      "entry_mcap_usd": 173604.0,
      "entry_price_usd": 0.0001736,
      "entry_liquidity_usd": 34345.78,
      "entry_top_holder_pct": 9.839561680702008,
      "entry_pair_dex": "pumpswap",
      "current_mcap_usd": 150960.0,
      "current_price_usd": 0.0001509,
      "current_liquidity_usd": 32768.54,
      "pct_from_call": -13.076036866359441
    },
    {
      "id": 23,
      "mint": "79YC3BkcgHKVg7imkadkVFu2kDRK3V6RUQ2iLFogpump",
      "symbol": "MEOWJESTY",
      "classification": "STAIRCASE",
      "confidence": 77,
      "called_at": 1777187490,
      "expires_at": 1778397090,
      "note": "",
      "source": "notifier",
      "status": "active",
      "outcome_type": "active",
      "closed_at": null,
      "exit_price_usd": null,
      "exit_note": null,
      "entry_mcap_usd": 169125.0,
      "entry_price_usd": 0.0001691,
      "entry_liquidity_usd": 35216.88,
      "entry_top_holder_pct": 10.843329727832629,
      "entry_pair_dex": "pumpswap",
      "current_mcap_usd": 5394.0,
      "current_price_usd": 5.394e-6,
      "current_liquidity_usd": 6328.54,
      "pct_from_call": -96.81017149615612
    },
    {
      "id": 22,
      "mint": "3hPjuKcU2Bs2hGnwrkNnYFnmkUbJNsaPpM6MzRH7pump",
      "symbol": "Dunald",
      "classification": "STAIRCASE",
      "confidence": 77,
      "called_at": 1777187390,
      "expires_at": 1778396990,
      "note": "",
      "source": "notifier",
      "status": "active",
      "outcome_type": "active",
      "closed_at": null,
      "exit_price_usd": null,
      "exit_note": null,
      "entry_mcap_usd": 351126.0,
      "entry_price_usd": 0.0003511,
      "entry_liquidity_usd": 51947.18,
      "entry_top_holder_pct": 7.2620280441729275,
      "entry_pair_dex": "pumpswap",
      "current_mcap_usd": 394479.0,
      "current_price_usd": 0.0003944,
      "current_liquidity_usd": 55351.26,
      "pct_from_call": 12.33266875534036
    },
    {
      "id": 21,
      "mint": "BFiGUxnidogqcZAPVPDZRCfhx3nXnFLYqpQUaUGpump",
      "symbol": "SPIKE",
      "classification": "STAIRCASE",
      "confidence": 77,
      "called_at": 1777186941,
      "expires_at": 1778396541,
      "note": "",
      "source": "notifier",
      "status": "active",
      "outcome_type": "active",
      "closed_at": null,
      "exit_price_usd": null,
      "exit_note": null,
      "entry_mcap_usd": 15825486.0,
      "entry_price_usd": 0.01582,
      "entry_liquidity_usd": 452009.58,
      "entry_top_holder_pct": 1.4272144597047223,
      "entry_pair_dex": "pumpswap",
      "current_mcap_usd": 15188751.0,
      "current_price_usd": 0.01518,
      "current_liquidity_usd": 443268.29,
      "pct_from_call": -4.045512010113783
    },
    {
      "id": 20,
      "mint": "89S7oVB4hui8ceJqhHreWB7fcxdthfvoB7z2pfJtpump",
      "symbol": "abcdefg",
      "classification": "STAIRCASE",
      "confidence": 75,
      "called_at": 1777186726,
      "expires_at": 1778396326,
      "note": "",
      "source": "notifier",
      "status": "active",
      "outcome_type": "active",
      "closed_at": null,
      "exit_price_usd": null,
      "exit_note": null,
      "entry_mcap_usd": 614111.0,
      "entry_price_usd": 0.0006169,
      "entry_liquidity_usd": 101283.8,
      "entry_top_holder_pct": 8.247347717191875,
      "entry_pair_dex": "pumpswap",
      "current_mcap_usd": 600496.0,
      "current_price_usd": 0.0006033,
      "current_liquidity_usd": 100218.18,
      "pct_from_call": -2.204571243313347
    },
    {
      "id": 19,
      "mint": "CJUrENDAuSm4FxxziUgftnUJqqXjm4VL1zhJgwXupump",
      "symbol": "HENRY",
      "classification": "STAIRCASE",
      "confidence": 77,
      "called_at": 1777186356,
      "expires_at": 1778395956,
      "note": "",
      "source": "notifier",
      "status": "active",
      "outcome_type": "active",
      "closed_at": null,
      "exit_price_usd": null,
      "exit_note": null,
      "entry_mcap_usd": 990257.0,
      "entry_price_usd": 0.0009902,
      "entry_liquidity_usd": 110523.73,
      "entry_top_holder_pct": 4.49902380282853,
      "entry_pair_dex": "meteora",
      "current_mcap_usd": 772819.0,
      "current_price_usd": 0.0007728,
      "current_liquidity_usd": 94131.47,
      "pct_from_call": -21.9551605736215
    },
    {
      "id": 18,
      "mint": "5gTPspC2ricuGWiYQ4Ghausg8fsq7uCrGgSVACatcoin",
      "symbol": "CATCOIN",
      "classification": "STAIRCASE",
      "confidence": 75,
      "called_at": 1777186250,
      "expires_at": 1778395850,
      "note": "",
      "source": "notifier",
      "status": "active",
      "outcome_type": "active",
      "closed_at": null,
      "exit_price_usd": null,
      "exit_note": null,
      "entry_mcap_usd": 814545.0,
      "entry_price_usd": 0.0008145,
      "entry_liquidity_usd": 81996.98,
      "entry_top_holder_pct": 5.038954430846812,
      "entry_pair_dex": "pumpswap",
      "current_mcap_usd": 843542.0,
      "current_price_usd": 0.0008435,
      "current_liquidity_usd": 83659.8,
      "pct_from_call": 3.560466543891949
    },
    {
      "id": 17,
      "mint": "BnXWvsVZYgBxTUDyDqHZjvFbQGvEZeipY4ZdmqCbpump",
      "symbol": "assface",
      "classification": "STAIRCASE",
      "confidence": 77,
      "called_at": 1777186249,
      "expires_at": 1778395849,
      "note": "",
      "source": "notifier",
      "status": "active",
      "outcome_type": "active",
      "closed_at": null,
      "exit_price_usd": null,
      "exit_note": null,
      "entry_mcap_usd": 707460.0,
      "entry_price_usd": 0.0007503,
      "entry_liquidity_usd": 95893.19,
      "entry_top_holder_pct": 6.3945404020089125,
      "entry_pair_dex": "pumpswap",
      "current_mcap_usd": 684894.0,
      "current_price_usd": 0.0007263,
      "current_liquidity_usd": 94464.41,
      "pct_from_call": -3.198720511795272
    },
    {
      "id": 16,
      "mint": "7KunmzqV5sbK8awVSjNjC3TGS9QPwbgCyrPynZBYpump",
      "symbol": "Kiss",
      "classification": "STAIRCASE",
      "confidence": 75,
      "called_at": 1777186055,
      "expires_at": 1778395655,
      "note": "",
      "source": "notifier",
      "status": "active",
      "outcome_type": "active",
      "closed_at": null,
      "exit_price_usd": null,
      "exit_note": null,
      "entry_mcap_usd": 89744.0,
      "entry_price_usd": 0.00008974,
      "entry_liquidity_usd": 23408.23,
      "entry_top_holder_pct": 12.989367235010501,
      "entry_pair_dex": "pumpswap",
      "current_mcap_usd": 1926.0,
      "current_price_usd": 1.926e-6,
      "current_liquidity_usd": 3435.69,
      "pct_from_call": -97.85379986628037
    },
    {
      "id": 15,
      "mint": "7WRX5QGuRLhGCJszpQjYmw6ihb6z8KRdAEHQUhGJpump",
      "symbol": "SAM",
      "classification": "STAIRCASE",
      "confidence": 75,
      "called_at": 1777186029,
      "expires_at": 1778395629,
      "note": "",
      "source": "notifier",
      "status": "active",
      "outcome_type": "active",
      "closed_at": null,
      "exit_price_usd": null,
      "exit_note": null,
      "entry_mcap_usd": 1068362.0,
      "entry_price_usd": 0.001068,
      "entry_liquidity_usd": 112974.02,
      "entry_top_holder_pct": 5.245865924490866,
      "entry_pair_dex": "pumpswap",
      "current_mcap_usd": 906907.0,
      "current_price_usd": 0.0009069,
      "current_liquidity_usd": 104241.26,
      "pct_from_call": -15.084269662921345
    },
    {
      "id": 14,
      "mint": "y8f9WhcWuaYoXfNGkaRCp3DunfygQoWGHjRooVGpump",
      "symbol": "WIZ",
      "classification": "STAIRCASE",
      "confidence": 75,
      "called_at": 1777185734,
      "expires_at": 1778395334,
      "note": "",
      "source": "notifier",
      "status": "active",
      "outcome_type": "active",
      "closed_at": null,
      "exit_price_usd": null,
      "exit_note": null,
      "entry_mcap_usd": 450596.0,
      "entry_price_usd": 0.0004742,
      "entry_liquidity_usd": 64527.11,
      "entry_top_holder_pct": 7.165918159955012,
      "entry_pair_dex": "pumpswap",
      "current_mcap_usd": 368485.0,
      "current_price_usd": 0.0003878,
      "current_liquidity_usd": 58512.09,
      "pct_from_call": -18.2201602699283
    },
    {
      "id": 13,
      "mint": "4df1wZoygsynEZ6XmpcoabrVwv7nBgjHLyCns5xApump",
      "symbol": "BELKA",
      "classification": "STAIRCASE",
      "confidence": 76,
      "called_at": 1777185309,
      "expires_at": 1778394909,
      "note": "",
      "source": "notifier",
      "status": "active",
      "outcome_type": "active",
      "closed_at": null,
      "exit_price_usd": null,
      "exit_note": null,
      "entry_mcap_usd": 751847.0,
      "entry_price_usd": 0.0007518,
      "entry_liquidity_usd": 74612.88,
      "entry_top_holder_pct": 4.956462700065297,
      "entry_pair_dex": "pumpswap",
      "current_mcap_usd": 1491542.0,
      "current_price_usd": 0.001491,
      "current_liquidity_usd": 106083.19,
      "pct_from_call": 98.32402234636872
    },
    {
      "id": 12,
      "mint": "3VHgeZygXSaXhzWzb2VoBNXu8AUCobLcQdTYPYFMpump",
      "symbol": "LASTWOMAN",
      "classification": "STAIRCASE",
      "confidence": 75,
      "called_at": 1777185149,
      "expires_at": 1778394749,
      "note": "",
      "source": "notifier",
      "status": "active",
      "outcome_type": "active",
      "closed_at": null,
      "exit_price_usd": null,
      "exit_note": null,
      "entry_mcap_usd": 150055.0,
      "entry_price_usd": 0.00015,
      "entry_liquidity_usd": 32674.41,
      "entry_top_holder_pct": 10.946491922896339,
      "entry_pair_dex": "pumpswap",
      "current_mcap_usd": 76516.0,
      "current_price_usd": 0.00007651,
      "current_liquidity_usd": 23605.54,
      "pct_from_call": -48.99333333333333
    },
    {
      "id": 11,
      "mint": "Hon2rHAiqkcDtUzL5gA2vjXPr7T1MPCK2UT2AHKCpump",
      "symbol": "MAGA",
      "classification": "STAIRCASE",
      "confidence": 75,
      "called_at": 1777184947,
      "expires_at": 1778394547,
      "note": "",
      "source": "notifier",
      "status": "active",
      "outcome_type": "active",
      "closed_at": null,
      "exit_price_usd": null,
      "exit_note": null,
      "entry_mcap_usd": 19593124.0,
      "entry_price_usd": 0.02002,
      "entry_liquidity_usd": 466304.26,
      "entry_top_holder_pct": 2.2617184121552554,
      "entry_pair_dex": "pumpswap",
      "current_mcap_usd": 18332870.0,
      "current_price_usd": 0.01874,
      "current_liquidity_usd": 451467.97,
      "pct_from_call": -6.3936063936063885
    },
    {
      "id": 10,
      "mint": "32CdQdBUxbCsLy5AUHWmyidfwhgGUr9N573NBUrDpump",
      "symbol": "maxxing",
      "classification": "STAIRCASE",
      "confidence": 76,
      "called_at": 1777184938,
      "expires_at": 1778394538,
      "note": "",
      "source": "notifier",
      "status": "active",
      "outcome_type": "active",
      "closed_at": null,
      "exit_price_usd": null,
      "exit_note": null,
      "entry_mcap_usd": 3563609.0,
      "entry_price_usd": 0.003564,
      "entry_liquidity_usd": 277008.86,
      "entry_top_holder_pct": 3.890505189225244,
      "entry_pair_dex": "pumpswap",
      "current_mcap_usd": 3728149.0,
      "current_price_usd": 0.003729,
      "current_liquidity_usd": 283831.08,
      "pct_from_call": 4.629629629629628
    },
    {
      "id": 9,
      "mint": "8AChxn68fMqyXTx9fWhPMnbc6Fua5NCkfBUin6Mdpump",
      "symbol": "Trump",
      "classification": "STAIRCASE",
      "confidence": 77,
      "called_at": 1777184909,
      "expires_at": 1778394509,
      "note": "",
      "source": "notifier",
      "status": "active",
      "outcome_type": "active",
      "closed_at": null,
      "exit_price_usd": null,
      "exit_note": null,
      "entry_mcap_usd": 371121.0,
      "entry_price_usd": 0.0003711,
      "entry_liquidity_usd": 50776.54,
      "entry_top_holder_pct": 9.35489086434079,
      "entry_pair_dex": "pumpswap",
      "current_mcap_usd": 284923.0,
      "current_price_usd": 0.0002849,
      "current_liquidity_usd": 45305.73,
      "pct_from_call": -23.228240366478047
    },
    {
      "id": 8,
      "mint": "Eno6h8oq9HaTKSHtLpXGa7iikjhJ3o7h9Za9ZfBspump",
      "symbol": "Iwunka",
      "classification": "STAIRCASE",
      "confidence": 77,
      "called_at": 1777184796,
      "expires_at": 1778394396,
      "note": "",
      "source": "notifier",
      "status": "active",
      "outcome_type": "active",
      "closed_at": null,
      "exit_price_usd": null,
      "exit_note": null,
      "entry_mcap_usd": 117512.0,
      "entry_price_usd": 0.0001175,
      "entry_liquidity_usd": 28514.26,
      "entry_top_holder_pct": 12.298089346820964,
      "entry_pair_dex": "pumpswap",
      "current_mcap_usd": 85820.0,
      "current_price_usd": 0.00008581,
      "current_liquidity_usd": 24653.49,
      "pct_from_call": -26.970212765957445
    },
    {
      "id": 7,
      "mint": "CGEDT9QZDvvH5GmVkWJH2BXiMJqMJySC9ihWyr7Spump",
      "symbol": "BURNIE",
      "classification": "STAIRCASE",
      "confidence": 77,
      "called_at": 1777184748,
      "expires_at": 1778394348,
      "note": "",
      "source": "notifier",
      "status": "active",
      "outcome_type": "active",
      "closed_at": null,
      "exit_price_usd": null,
      "exit_note": null,
      "entry_mcap_usd": 17222271.0,
      "entry_price_usd": 0.01775,
      "entry_liquidity_usd": 535829.16,
      "entry_top_holder_pct": 3.93114497872959,
      "entry_pair_dex": "pumpswap",
      "current_mcap_usd": 16868666.0,
      "current_price_usd": 0.01739,
      "current_liquidity_usd": 530834.1,
      "pct_from_call": -2.028169014084502
    },
    {
      "id": 6,
      "mint": "Uzb8hB1YWAUzpd6w5aASEfBgS6yEq7Kyaam7VJgpump",
      "symbol": "Shooter",
      "classification": "STAIRCASE",
      "confidence": 75,
      "called_at": 1777175888,
      "expires_at": 1778385488,
      "note": "",
      "source": "notifier",
      "status": "active",
      "outcome_type": "active",
      "closed_at": null,
      "exit_price_usd": null,
      "exit_note": null,
      "entry_mcap_usd": 256493.0,
      "entry_price_usd": 0.0002564,
      "entry_liquidity_usd": 40253.93,
      "entry_top_holder_pct": 7.987350565007301,
      "entry_pair_dex": "pumpswap",
      "current_mcap_usd": 1748.0,
      "current_price_usd": 1.748e-6,
      "current_liquidity_usd": 3443.86,
      "pct_from_call": -99.31825273010921
    }
  ],
  "history": [
    {
      "id": 5,
      "mint": "Hct14sMUim2d9pZDV9HWjynhidWr8KE4yvdxss9bpump",
      "symbol": "ALEXCOIN",
      "classification": "STAIRCASE",
      "confidence": 75,
      "called_at": 1777162239,
      "expires_at": 1778371839,
      "note": "",
      "source": "notifier",
      "status": "failed",
      "outcome_type": "failed",
      "closed_at": 1777184478,
      "exit_price_usd": 0.00007995,
      "exit_note": "auto-failed: orphaned call (watchlist inactive at startup)",
      "entry_mcap_usd": 114949.0,
      "entry_price_usd": 0.0001181,
      "entry_liquidity_usd": 27209.27,
      "entry_top_holder_pct": 11.682623647150828,
      "entry_pair_dex": "pumpswap",
      "current_mcap_usd": 0.0,
      "current_price_usd": 0.00007995,
      "current_liquidity_usd": 0.0,
      "pct_from_call": -32.30313293818797
    },
    {
      "id": 4,
      "mint": "BmXVrGfDa2dTTbdSfcw1QpSWym4wJtNJqPbNjLkepump",
      "symbol": "Rudy",
      "classification": "STAIRCASE",
      "confidence": 75,
      "called_at": 1777160525,
      "expires_at": 1778370125,
      "note": "",
      "source": "notifier",
      "status": "failed",
      "outcome_type": "failed",
      "closed_at": 1777184478,
      "exit_price_usd": 0.0000284,
      "exit_note": "auto-failed: orphaned call (watchlist inactive at startup)",
      "entry_mcap_usd": 204639.0,
      "entry_price_usd": 0.0002046,
      "entry_liquidity_usd": 38306.23,
      "entry_top_holder_pct": 9.47267576058295,
      "entry_pair_dex": "pumpswap",
      "current_mcap_usd": 0.0,
      "current_price_usd": 0.0000284,
      "current_liquidity_usd": 0.0,
      "pct_from_call": -86.11925708699903
    },
    {
      "id": 3,
      "mint": "5YNnwMzbFtL75ocUxFYhwFDU5vywMHArET8ed3tGXuMu",
      "symbol": "Rudi",
      "classification": "STAIRCASE",
      "confidence": 81,
      "called_at": 1777067069,
      "expires_at": null,
      "note": "[auto] STAIRCASE conf=81 mom=80 top=4.5% mcap=1060k liq=94k horizon=SHORT",
      "source": "auto",
      "status": "failed",
      "outcome_type": "failed",
      "closed_at": 1777092986,
      "exit_price_usd": 0.00003427,
      "exit_note": "auto-failed: orphaned — watchlist deactivated before auto-fail hook deployed; down -96.8%",
      "entry_mcap_usd": 1060083.0,
      "entry_price_usd": 0.00106,
      "entry_liquidity_usd": 93772.17,
      "entry_top_holder_pct": 4.5085011798964,
      "entry_pair_dex": "raydium",
      "current_mcap_usd": 0.0,
      "current_price_usd": 0.00003427,
      "current_liquidity_usd": 0.0,
      "pct_from_call": -96.76698113207547
    },
    {
      "id": 2,
      "mint": "8BbZu1vPCh2iPpXynKKHzx1gFzyuAWGGXoqtUJ9Tpump",
      "symbol": "Michael",
      "classification": "STAIRCASE",
      "confidence": 75,
      "called_at": 1776878762,
      "expires_at": 1778088362,
      "note": "",
      "source": "notifier",
      "status": "closed",
      "outcome_type": "withdrew",
      "closed_at": 1776891329,
      "exit_price_usd": 0.00005896,
      "exit_note": "retracted — notifier promoted a raw signal before the deep wallet/holder/market audit thesis existed",
      "entry_mcap_usd": 74502.0,
      "entry_price_usd": 0.00007451,
      "entry_liquidity_usd": 22292.71,
      "entry_top_holder_pct": 14.969489798639051,
      "entry_pair_dex": "pumpswap",
      "current_mcap_usd": 0.0,
      "current_price_usd": 0.00005896,
      "current_liquidity_usd": 0.0,
      "pct_from_call": -20.869681921889683
    },
    {
      "id": 1,
      "mint": "2nP9yKQNSGQy851iyawDvBkzkK2R2aqKArQCKc2gpump",
      "symbol": "PsyopAnime",
      "classification": "MANUAL",
      "confidence": 0,
      "called_at": 1776820045,
      "expires_at": 1778029645,
      "note": "PsyopAnime $PSYOPANIME — first call. Thesis: one real trader (692PxWKE…) accumulated ~4.77% of supply, +1.19M/24h and +9.09M/7d, absorbing a sell-heavy tape (h24 873b/998s). Bear case survives: 447-account insider network = 30.96% supply. Trigger to monitor publicly: 692PxWKE flow + RugCheck insider network dilution. Exit ladder: 25% at +40%, 25% at +80%, 25% at +150%, 25% runner with 14-day hard close.",
      "source": "mcp",
      "status": "failed",
      "outcome_type": "failed",
      "closed_at": 1777094849,
      "exit_price_usd": 0.002243,
      "exit_note": "auto-failed: orphaned call (watchlist inactive at startup)",
      "entry_mcap_usd": 2274601.0,
      "entry_price_usd": 0.002274,
      "entry_liquidity_usd": 248918.42,
      "entry_top_holder_pct": 5.476964713464018,
      "entry_pair_dex": "pumpswap",
      "current_mcap_usd": 0.0,
      "current_price_usd": 0.002243,
      "current_liquidity_usd": 0.0,
      "pct_from_call": -1.3632365875109853
    }
  ]
}