{
  "positions": [
    {
      "mint": "9iStGeYTqTsxxx1p1GuZK73Uzh9spBcHYu3Y1suopump",
      "symbol": "MAAI",
      "balance_ui": 10000000.0,
      "avg_entry_usd": 2.496500098214e-6,
      "current_price_usd": 2.779e-6,
      "position_usd": 27.79,
      "pnl_pct": 11.315837799810247
    },
    {
      "mint": "91kDvTYSe6QwxsGpBqnjWWek6bpTc7ktV692yHLipump",
      "symbol": "nugget",
      "balance_ui": 308682.196446,
      "avg_entry_usd": 0.000014459919178788256,
      "current_price_usd": 0.00004206,
      "position_usd": 12.98317318251876,
      "pnl_pct": 190.8729950697044
    },
    {
      "mint": "2Fiut5a3s7vBkGFKXd7kH2v8W1idJ9g7CWAvMEdVpump",
      "symbol": "GAY",
      "balance_ui": 255242.913987,
      "avg_entry_usd": 0.00003340390391662058,
      "current_price_usd": 0.00003274,
      "position_usd": 8.356653003934381,
      "pnl_pct": -1.9875039704273734
    },
    {
      "mint": "4eviw9nB6qx7z3hSF1hMv9ViTrzzhbsKFtAm88EPBAGS",
      "symbol": "SPIRIT",
      "balance_ui": 240546.302148096,
      "avg_entry_usd": 0.000030027064479973223,
      "current_price_usd": 0.00002523,
      "position_usd": 6.068983203196463,
      "pnl_pct": -15.975802373797343
    }
  ]
}