{
  "events": [
    {
      "ts": 1777744561,
      "kind": "alert",
      "tag": "DEV SELLING",
      "summary": "DEV_SELLING GnqR…pump · deployer down 87.1% (479523704 → 61781062)",
      "mint": "GnqRKyQfcna6XbkoJMKkvUZUBQdtMb8oy5rH2ocpump",
      "signature": null
    },
    {
      "ts": 1777744544,
      "kind": "alert",
      "tag": "DEV SELLING",
      "summary": "DEV_SELLING 4KeZ…pump · deployer down 100.0% (235305891 → 0)",
      "mint": "4KeZZMNeW1xqG8trwu7KaJivzLf8S1vyeJzpU2JHpump",
      "signature": null
    },
    {
      "ts": 1777744541,
      "kind": "alert",
      "tag": "DEV SELLING",
      "summary": "DEV_SELLING GnqR…pump · deployer down 87.1% (479523704 → 61781062)",
      "mint": "GnqRKyQfcna6XbkoJMKkvUZUBQdtMb8oy5rH2ocpump",
      "signature": null
    },
    {
      "ts": 1777744522,
      "kind": "alert",
      "tag": "DEV SELLING",
      "summary": "DEV_SELLING 4KeZ…pump · deployer down 100.0% (235305891 → 0)",
      "mint": "4KeZZMNeW1xqG8trwu7KaJivzLf8S1vyeJzpU2JHpump",
      "signature": null
    },
    {
      "ts": 1777744518,
      "kind": "alert",
      "tag": "DEV SELLING",
      "summary": "DEV_SELLING GnqR…pump · deployer down 85.8% (479523704 → 68087448)",
      "mint": "GnqRKyQfcna6XbkoJMKkvUZUBQdtMb8oy5rH2ocpump",
      "signature": null
    },
    {
      "ts": 1777744500,
      "kind": "alert",
      "tag": "DEV SELLING",
      "summary": "DEV_SELLING 4KeZ…pump · deployer down 100.0% (235305891 → 0)",
      "mint": "4KeZZMNeW1xqG8trwu7KaJivzLf8S1vyeJzpU2JHpump",
      "signature": null
    }
  ],
  "tokens": {
    "4KeZZMNeW1xqG8trwu7KaJivzLf8S1vyeJzpU2JHpump": {
      "symbol": "Farmer",
      "name": "Farmer",
      "mcap_usd": 7261.0,
      "price_usd": 7.26e-6,
      "price_change_1h": -79.05,
      "price_change_24h": null,
      "liquidity_usd": 6559.39
    },
    "CLJJs8pSkSkgHvzeZRoS1Jkge7SxPhd9LrJmArvSpump": {
      "symbol": "LGBT",
      "name": "Luigi Got Big Titties ",
      "mcap_usd": 48500.0,
      "price_usd": 0.00004849,
      "price_change_1h": 40.02,
      "price_change_24h": null,
      "liquidity_usd": 17012.0
    },
    "6P18kpmUZbm3YKeq7PqVyrxz1eEUmAUjqqMqrdWoTQjT": {
      "symbol": "HODLERS",
      "name": "The Hodlers",
      "mcap_usd": 59696.0,
      "price_usd": 0.00005969,
      "price_change_1h": 72.4,
      "price_change_24h": null,
      "liquidity_usd": 19057.68
    },
    "axUxN2q4AWzHaU6LXmjqQh7KEjaXDPKScjmzwEBpump": {
      "symbol": "Grandma",
      "name": "Minecraft Grandma Fund",
      "mcap_usd": 340834.0,
      "price_usd": 0.0003408,
      "price_change_1h": -1.22,
      "price_change_24h": null,
      "liquidity_usd": 72993.41
    },
    "W1NqGUNfaxJpiKeeu9p8yxZNomPaC1ugLHeZ5ZvKC4m": {
      "symbol": "WINNING",
      "name": "WINNING",
      "mcap_usd": 125603.0,
      "price_usd": 0.0001256,
      "price_change_1h": 58.75,
      "price_change_24h": null,
      "liquidity_usd": 27346.55
    },
    "3hHZ3QFWKVgUdi64uHJumK9T7hDR2Tr6WZBjUfP5pump": {
      "symbol": "FINE",
      "name": "This is Fine",
      "mcap_usd": 74911.0,
      "price_usd": 0.00007491,
      "price_change_1h": 60.89,
      "price_change_24h": null,
      "liquidity_usd": 21105.37
    },
    "GnqRKyQfcna6XbkoJMKkvUZUBQdtMb8oy5rH2ocpump": {
      "symbol": "MSTRUMP",
      "name": "MS Paint Trump",
      "mcap_usd": 114279.0,
      "price_usd": 0.0001142,
      "price_change_1h": 37.5,
      "price_change_24h": null,
      "liquidity_usd": 26385.57
    }
  },
  "watching": [
    {
      "mint": "W1NqGUNfaxJpiKeeu9p8yxZNomPaC1ugLHeZ5ZvKC4m",
      "symbol": "WINNING",
      "classification": "STAIRCASE",
      "confidence": 80,
      "top_holder_pct": 10.7126137134637,
      "age_secs": 303,
      "gate": "sniper",
      "gap": "sniper 93.3% >= 60.0%",
      "last_seen": 1777744261
    },
    {
      "mint": "axUxN2q4AWzHaU6LXmjqQh7KEjaXDPKScjmzwEBpump",
      "symbol": "Grandma",
      "classification": "GRINDER",
      "confidence": 78,
      "top_holder_pct": 11.500214853039353,
      "age_secs": 1,
      "gate": "tx_rate",
      "gap": "txr 0.5/min < 5.0 (short by 4.5)",
      "last_seen": 1777744563
    },
    {
      "mint": "3hHZ3QFWKVgUdi64uHJumK9T7hDR2Tr6WZBjUfP5pump",
      "symbol": "FINE",
      "classification": "STAIRCASE",
      "confidence": 76,
      "top_holder_pct": 14.268664366161001,
      "age_secs": 108,
      "gate": "top10",
      "gap": "top10 85.1% >= 50.0% (over by 35.1pp)",
      "last_seen": 1777744456
    },
    {
      "mint": "CLJJs8pSkSkgHvzeZRoS1Jkge7SxPhd9LrJmArvSpump",
      "symbol": "LGBT",
      "classification": "STAIRCASE",
      "confidence": 71,
      "top_holder_pct": 18.082757625895955,
      "age_secs": 2,
      "gate": "sniper",
      "gap": "sniper 70.2% >= 60.0%",
      "last_seen": 1777744562
    },
    {
      "mint": "6P18kpmUZbm3YKeq7PqVyrxz1eEUmAUjqqMqrdWoTQjT",
      "symbol": "HODLERS",
      "classification": "GRINDER",
      "confidence": 67,
      "top_holder_pct": 15.760875477210012,
      "age_secs": 23,
      "gate": "momentum_delta",
      "gap": "mom_delta -3 < 0",
      "last_seen": 1777744541
    }
  ]
}